treescript/__init__.py
treescript/exceptions.py
treescript/mercurial.py
treescript/script.py
treescript/task.py
treescript/utils.py
treescript/versionmanip.py
treescript/data/hgrc
treescript/data/treescript_task_schema.json
treescript/py2/robustcheckout.py
treescript/test/__init__.py
treescript/test/test_exceptions.py
treescript/test/test_mercurial.py
treescript/test/test_robustcheckout.py
treescript/test/test_script.py
treescript/test/test_task.py
treescript/test/test_utils.py
treescript/test/test_versionmanip.py
treescript-1.2.1.dist-info/LICENSE
treescript-1.2.1.dist-info/METADATA
treescript-1.2.1.dist-info/WHEEL
treescript-1.2.1.dist-info/entry_points.txt
treescript-1.2.1.dist-info/top_level.txt
treescript-1.2.1.dist-info/RECORD
